pcst_fast.cpython-311-darwin.so
pcst_fast/pairing_heap.h
pcst_fast/pcst_fast.cc
pcst_fast/pcst_fast.h
pcst_fast/pcst_fast_pybind.cc
pcst_fast/pcst_fast_test.cc
pcst_fast/priority_queue.h
pcst_fast/test_helpers.h
pcst_fast/test_pcst_fast.py
pcstf-1.0.10.post1.dist-info/LICENSE
pcstf-1.0.10.post1.dist-info/METADATA
pcstf-1.0.10.post1.dist-info/WHEEL
pcstf-1.0.10.post1.dist-info/top_level.txt
pcstf-1.0.10.post1.dist-info/RECORD
