Metadata-Version: 2.1
Name: pcstf
Version: 1.0.10.post1
Summary: A fast implementation of the Goemans-Williamson scheme for the prize-collecting Steiner tree / forest problem.
Home-page: https://github.com/fraenkel-lab/pcst_fast
Author: Harshith Manjunath
Author-email: harshith.manjunath@fau.de
License: GNU General Public License
Requires-Python: >=3.8
License-File: LICENSE
Requires-Dist: setuptools (>=40.8.0)
Requires-Dist: pybind11 (>=2.1.0)
